LICENSE
MANIFEST.in
README
requirements.txt
setup.cfg
setup.py
pylam/__init__.py
pylam/_block.py
pylam/_datafile.py
pylam/_lmpdatafile.py
pylam/_thermodat.py
pylam/version.py
pylam.egg-info/PKG-INFO
pylam.egg-info/SOURCES.txt
pylam.egg-info/dependency_links.txt
pylam.egg-info/requires.txt
pylam.egg-info/top_level.txt
pylam/base/__init__.py
pylam/base/blockfile.py
pylam/base/indexedfile.py
pylam/base/table.py
pylam/dev/__init__.py
pylam/dev/_blockave.py