Metadata-Version: 1.1
Name: pylam
Version: 0.1.6
Summary: A python library for working with in and out put files for respectively generated by LAMMPS.
Home-page: http://wgserve.de/pylam
Author: Frank Roemer
Author-email: froemer76@googlemail.com
License: MIT
Keywords: LAMMPS
Platform: UNKNOWN
Classifier: Operating System :: OS Independent
Classifier: Development Status :: 2 - Pre-Alpha
Classifier: License :: OSI Approved :: MIT License
Classifier: Intended Audience :: Developers
Classifier: Topic :: Software Development :: Libraries :: Python Modules
Classifier: Programming Language :: Python :: 2.7
